numla/__init__.py
numla/arithmetic.py
numla/functions.py
numla/larry.py
numla/signals.py
numla-0.0.1.dist-info/METADATA
numla-0.0.1.dist-info/WHEEL
numla-0.0.1.dist-info/licenses/LICENSE
numla-0.0.1.dist-info/RECORD
