Metadata-Version: 2.1
Name: numla
Version: 0.0.1
Summary: Fast numpy LAbeled aRRaY for financial time series data. Simply load, slice, cache, and analyze. Accelerators: C, Numba, Vectorization.
Project-URL: Homepage, https://github.com/flockrush/numla
Project-URL: Bug Tracker, https://github.com/flockrush/numla/issues
Author-email: Flockrush <team@flockrush.com>
License-File: LICENSE
Classifier: Development Status :: 1 - Planning
Classifier: Intended Audience :: Science/Research
Classifier: License :: OSI Approved :: BSD License
Classifier: Operating System :: OS Independent
Classifier: Programming Language :: Python :: 3
Requires-Python: >=3.10
